cap/__init__.py
cap/cap_config.py
cap/cap_exception.py
cap/cap_publisher.py
cap/cap_storage.py
tests/__init__.py
tests/cap_test.py
CoCap-0.1.1.dist-info/LICENSE.txt
CoCap-0.1.1.dist-info/METADATA
CoCap-0.1.1.dist-info/WHEEL
CoCap-0.1.1.dist-info/top_level.txt
CoCap-0.1.1.dist-info/RECORD
