Metadata-Version: 2.1
Name: CoCap
Version: 0.1.1
Summary: CAP
Home-page: https://www.cityocean.com
Author: CityOcean
Author-email: it@cityocean.com
License: GPL
Keywords: rabbitmq,cap
Platform: UNKNOWN
Classifier: Intended Audience :: Developers
Classifier: License :: OSI Approved :: BSD License
Classifier: Programming Language :: Python
Classifier: Programming Language :: Python :: 3.8
Classifier: Programming Language :: Python :: 3.9
Classifier: Operating System :: OS Independent
Classifier: Topic :: Software Development :: Libraries :: Python Modules
Requires-Python: >=3.6
License-File: LICENSE.txt
